Metadata-Version: 1.1
Name: visonicalarm80
Version: 3.0.7
Summary: A simple API library for the Visonic Alarm system.
Home-page: https://github.com/And3rsL/VisonicAlarm8.0
Author: Andrea Liosi
Author-email: andrea.liosi@gmail.com
License: UNKNOWN
Platform: UNKNOWN
Classifier: Programming Language :: Python :: 3
Classifier: License :: OSI Approved :: MIT License
Classifier: Operating System :: OS Independent
